dawson_college_pyscrapper/__init__.py
dawson_college_pyscrapper/constants.py
dawson_college_pyscrapper/exceptions.py
dawson_college_pyscrapper/models.py
dawson_college_pyscrapper/scrapper.py
dawson_college_pyscrapper/util.py
dawson_college_pyscrapper-1.1.1.dist-info/LICENSE.md
dawson_college_pyscrapper-1.1.1.dist-info/METADATA
dawson_college_pyscrapper-1.1.1.dist-info/WHEEL
dawson_college_pyscrapper-1.1.1.dist-info/top_level.txt
dawson_college_pyscrapper-1.1.1.dist-info/RECORD
