Metadata-Version: 2.1
Name: dawson-college-pyscrapper
Version: 1.1.1
Summary: A Python module which contains useful functions to help scrap data from Dawson College which is a CEGEP in Montreal Quebec Canada.
Maintainer-email: Jeffrey Boisvert <info.jeffreyboisvert@gmail.com>
Project-URL: repository, https://github.com/jdboisvert/dawson-college-pyscrapper
Platform: any
Requires-Python: >=3.8.0
License-File: LICENSE.md
Requires-Dist: beautifulsoup4 (==4.11.2)
Requires-Dist: pandas (==1.5.3)
Requires-Dist: requests (==2.28.2)
Provides-Extra: dev
Requires-Dist: setuptools (==58.1.0) ; extra == 'dev'
Requires-Dist: black (==22.6.0) ; extra == 'dev'
Requires-Dist: bumpver (==2021.1114) ; extra == 'dev'
Requires-Dist: coverage[toml] (==6.4.4) ; extra == 'dev'
Requires-Dist: isort (==5.9.3) ; extra == 'dev'
Requires-Dist: pydocstyle[toml] (==6.1.1) ; extra == 'dev'
Requires-Dist: pytest-cov (==3.0.0) ; extra == 'dev'
Requires-Dist: pytest (==6.2.4) ; extra == 'dev'
Requires-Dist: tox (==3.24.3) ; extra == 'dev'
Requires-Dist: twine (==3.4.2) ; extra == 'dev'
Requires-Dist: watchdog (==2.1.4) ; extra == 'dev'
Requires-Dist: wheel (==0.36.2) ; extra == 'dev'
Requires-Dist: toml (==0.10.2) ; extra == 'dev'
Requires-Dist: myst-parser (==0.18.0) ; extra == 'dev'
Requires-Dist: mock (==5.0.1) ; extra == 'dev'
Requires-Dist: pytest-mock (==3.10.0) ; extra == 'dev'
Requires-Dist: requests-mock (==1.10.0) ; extra == 'dev'
Requires-Dist: freezegun (==1.2.2) ; extra == 'dev'
